sgia/__init__.py
sgia-0.1.1.dist-info/LICENSE.txt
sgia-0.1.1.dist-info/METADATA
sgia-0.1.1.dist-info/WHEEL
sgia-0.1.1.dist-info/top_level.txt
sgia-0.1.1.dist-info/RECORD
