Metadata-Version: 2.1
Name: sgia
Version: 0.1.1
Summary: Sparse Grid Indexing Algorithm
Author-email: Nisanthan K <nisakathir@gmail.com>
Project-URL: Homepage, https://github.com/Nishaanthan/SGIA
Project-URL: Issues, https://github.com/Nishaanthan/SGIA/issues
Classifier: Programming Language :: Python :: 3
Classifier: License :: OSI Approved :: MIT License
Classifier: Operating System :: OS Independent
Requires-Python: >=3.6
License-File: LICENSE.txt
